odoo/addons/stock_report_quantity_by_location/README.rst
odoo/addons/stock_report_quantity_by_location/__init__.py
odoo/addons/stock_report_quantity_by_location/__manifest__.py
odoo/addons/stock_report_quantity_by_location/i18n/es_MX.po
odoo/addons/stock_report_quantity_by_location/i18n/fr.po
odoo/addons/stock_report_quantity_by_location/i18n/sk.po
odoo/addons/stock_report_quantity_by_location/i18n/sl.po
odoo/addons/stock_report_quantity_by_location/i18n/stock_report_quantity_by_location.pot
odoo/addons/stock_report_quantity_by_location/readme/CONTRIBUTORS.rst
odoo/addons/stock_report_quantity_by_location/readme/DESCRIPTION.rst
odoo/addons/stock_report_quantity_by_location/security/security.xml
odoo/addons/stock_report_quantity_by_location/static/description/icon.png
odoo/addons/stock_report_quantity_by_location/static/description/index.html
odoo/addons/stock_report_quantity_by_location/tests/__init__.py
odoo/addons/stock_report_quantity_by_location/tests/test_stock_report_quantity_by_location.py
odoo/addons/stock_report_quantity_by_location/wizards/__init__.py
odoo/addons/stock_report_quantity_by_location/wizards/stock_report_quantity_by_location.py
odoo/addons/stock_report_quantity_by_location/wizards/stock_report_quantity_by_location_views.xml
odoo12_addon_stock_report_quantity_by_location-12.0.1.0.1.dist-info/METADATA
odoo12_addon_stock_report_quantity_by_location-12.0.1.0.1.dist-info/WHEEL
odoo12_addon_stock_report_quantity_by_location-12.0.1.0.1.dist-info/top_level.txt
odoo12_addon_stock_report_quantity_by_location-12.0.1.0.1.dist-info/RECORD
